instatools/__init__.py
instatools/api.py
instatools/cache.py
instatools/models.py
instatools/session.py
instatools/instagram/__init__.py
instatools/instagram/feeds.py
instatools/instagram/hub.py
instatools/instagram/instagram.py
instatools/instagram/profile.py
instatools/instagram/search.py
instatools-0.1.8.dist-info/AUTHORS.rst
instatools-0.1.8.dist-info/LICENSE
instatools-0.1.8.dist-info/METADATA
instatools-0.1.8.dist-info/WHEEL
instatools-0.1.8.dist-info/entry_points.txt
instatools-0.1.8.dist-info/top_level.txt
instatools-0.1.8.dist-info/RECORD
