Metadata-Version: 2.1
Name: instatools
Version: 0.1.8
Summary: Unofficial Instagram API for python 3.5+
Home-page: https://github.com/sentrip/instatools
Author: Djordje Pepic
Author-email: djordje.m.pepic@gmail.com
License: GNU General Public License v3
Keywords: instatools
Platform: UNKNOWN
Classifier: Development Status :: 2 - Pre-Alpha
Classifier: Intended Audience :: Developers
Classifier: License :: OSI Approved :: GNU General Public License v3 (GPLv3)
Classifier: Natural Language :: English
Classifier: Programming Language :: Python :: 3.5
Classifier: Programming Language :: Python :: 3.6
Requires-Dist: requests (>=2.18.4)
Requires-Dist: ratelimiter (>=1.2.0)
Requires-Dist: cached-property (>=1.4.3)
Requires-Dist: pillow (>=5.1.0)
